setup.py
cobertura_aggregator/__init__.py
cobertura_aggregator/base.py
cobertura_aggregator/run.py
cobertura_aggregator.egg-info/PKG-INFO
cobertura_aggregator.egg-info/SOURCES.txt
cobertura_aggregator.egg-info/dependency_links.txt
cobertura_aggregator.egg-info/entry_points.txt
cobertura_aggregator.egg-info/requires.txt
cobertura_aggregator.egg-info/top_level.txt
cobertura_aggregator/tests/__init__.py
cobertura_aggregator/tests/api.py
cobertura_aggregator/tests/test_run.py
cobertura_aggregator/tests/xml.py