Metadata-Version: 1.0
Name: cobertura-aggregator
Version: 0.1
Summary: Cobertura folder coverage aggregator
Home-page: https://github.com/juannyg/cobertura_aggregator/
Author: Juan Gutierrez
Author-email: UNKNOWN
License: Creative Commons Attribution-Noncommercial-Share Alike license
Platform: UNKNOWN
